catsu/__init__.py
catsu/_catsu.cpython-310-x86_64-linux-gnu.so
catsu/py.typed
catsu-0.1.7.dist-info/METADATA
catsu-0.1.7.dist-info/WHEEL
catsu-0.1.7.dist-info/RECORD
