Metadata-Version: 2.4
Name: catsu
Version: 0.1.7
Classifier: Development Status :: 3 - Alpha
Classifier: Intended Audience :: Developers
Classifier: License :: OSI Approved :: Apache Software License
Classifier: Programming Language :: Rust
Classifier: Programming Language :: Python :: Implementation :: CPython
Classifier: Programming Language :: Python :: 3
Classifier: Programming Language :: Python :: 3.11
Classifier: Programming Language :: Python :: 3.12
Classifier: Programming Language :: Python :: 3.13
Classifier: Topic :: Scientific/Engineering :: Artificial Intelligence
Summary: High-performance embeddings client for multiple providers
Keywords: embeddings,openai,voyageai,async,rust
Author-email: Bhavnick Minhas <bhavnick@chonkie.ai>
License: Apache-2.0
Requires-Python: >=3.11
Project-URL: Homepage, https://github.com/chonkie-inc/catsu
Project-URL: Repository, https://github.com/chonkie-inc/catsu
